feautils/__init__.py
feautils/demand_profiles.py
feautils/general.py
feautils/plotting.py
feautils/timeseries.py
feautils-0.0.8.dist-info/LICENSE
feautils-0.0.8.dist-info/METADATA
feautils-0.0.8.dist-info/WHEEL
feautils-0.0.8.dist-info/RECORD
